cobaya_utilities/__init__.py
cobaya_utilities/_version.py
cobaya_utilities/fisher.py
cobaya_utilities/plots.py
cobaya_utilities/tools.py
cobaya_utilities/utilities.py
cobaya_utilities/tests/test_fisher.py
cobaya_utilities/tests/test_tools.py
cobaya_utilities/tests/utilities.py
cobaya_utilities/tests/data/fisher_ref.yaml
cobaya_utilities/tests/data/chains/mcmc.1.txt
cobaya_utilities/tests/data/chains/mcmc.covmat
cobaya_utilities/tests/data/chains/mcmc.log
cobaya_utilities/tests/data/chains/mcmc.progress
cobaya_utilities/tests/data/chains/mcmc.updated.yaml
docs/tutorials/chains.ipynb
docs/tutorials/fisher.ipynb
docs/tutorials/figures/print_chains_size.png
cobaya_utilities-0.3.5.dist-info/METADATA
cobaya_utilities-0.3.5.dist-info/WHEEL
cobaya_utilities-0.3.5.dist-info/top_level.txt
cobaya_utilities-0.3.5.dist-info/RECORD
