Metadata-Version: 2.4
Name: cobaya_utilities
Version: 0.3.5
Summary: A set of functions to deal with MCMC output from cobaya
Author: Xavier Garrido
Project-URL: Homepage, https://github.com/xgarrido/cobaya_utilities
Project-URL: Documentation, https://cobaya_utilities.readthedocs.io
Project-URL: Source, https://github.com/xgarrido/cobaya_utilities
Project-URL: Tracker, https://github.com/xgarrido/cobaya_utilities/issues
Project-URL: Licensing, https://github.com/xgarrido/cobaya_utilities/blob/master/LICENCE
Keywords: cobaya,MCMC,plot
Classifier: Intended Audience :: Developers
Classifier: License :: OSI Approved :: BSD License
Classifier: Natural Language :: English
Classifier: Programming Language :: Python :: 3.9
Classifier: Programming Language :: Python :: 3.10
Classifier: Programming Language :: Python :: 3.11
Classifier: Topic :: Scientific/Engineering :: Visualization
Classifier: Topic :: Education
Requires-Python: >=3.10.0
Requires-Dist: cobaya>=3.4.1
Requires-Dist: seaborn
Requires-Dist: tqdm
Requires-Dist: jinja2
Provides-Extra: test
Requires-Dist: pytest; extra == "test"
Requires-Dist: pytest-cov; extra == "test"
Requires-Dist: camb; extra == "test"
Requires-Dist: mflike; extra == "test"
Provides-Extra: notebook
Requires-Dist: jupyter; extra == "notebook"
Requires-Dist: camb; extra == "notebook"
Requires-Dist: latex2mathml; extra == "notebook"
